brython_components/__init__.py
brython_components/decorators.py
brython_components/elements.py
brython_components-0.3.1.dist-info/LICENSE
brython_components-0.3.1.dist-info/METADATA
brython_components-0.3.1.dist-info/WHEEL
brython_components-0.3.1.dist-info/RECORD
