Metadata-Version: 2.1
Name: brython-components
Version: 0.3.1
Summary: Brython-components is an easy implementation of brython's webcomonent
License: MIT
Keywords: brython,Development,webcomponents
Author: Lorenzo A. Garcia Calzadilla
Author-email: lorenzogarciacalzadilla@gmail.com
Requires-Python: >=3.10,<4.0
Classifier: Development Status :: 4 - Beta
Classifier: Environment :: Web Environment
Classifier: Intended Audience :: Developers
Classifier: License :: OSI Approved :: MIT License
Classifier: Programming Language :: Python :: 3
Classifier: Programming Language :: Python :: 3.10
Classifier: Programming Language :: Python :: 3.11
Classifier: Programming Language :: Python :: 3.12
Classifier: Programming Language :: Python :: Implementation
Classifier: Topic :: Software Development
Requires-Dist: waitress (>=2.1.2,<3.0.0)
